typing_dataclasses/__init__.py
typing_dataclasses/main.py
typing_dataclasses-0.1.0.dist-info/METADATA
typing_dataclasses-0.1.0.dist-info/WHEEL
typing_dataclasses-0.1.0.dist-info/RECORD
