Metadata-Version: 2.3
Name: typing-dataclasses
Version: 0.1.0
Summary: 
Author: roBoot-LDT
Author-email: maksim.nemkov.ldt@gmail.com
Requires-Python: >=3.13
Classifier: Programming Language :: Python :: 3
Classifier: Programming Language :: Python :: 3.13
